LICENSE
MANIFEST.in
README.md
install-requirements.txt
setup.py
hg_loggingmod.egg-info/PKG-INFO
hg_loggingmod.egg-info/SOURCES.txt
hg_loggingmod.egg-info/dependency_links.txt
hg_loggingmod.egg-info/requires.txt
hg_loggingmod.egg-info/top_level.txt
hgext3rd/__init__.py
hgext3rd/loggingmod/__init__.py
hgext3rd/loggingmod/config.py
hgext3rd/loggingmod/sentry.py
hgext3rd/loggingmod/version.py