Metadata-Version: 2.1
Name: hg-loggingmod
Version: 0.4.1
Summary: Managing Mercurial logs with the standard Python logging module
Home-page: https://dev.heptapod.net/heptapod/hgext-loggingmod
Author: Georges Racinet
Author-email: georges.racinet@octobus.net
License: GPLv2+
Keywords: hg mercurial
License-File: LICENSE
